dynamicmethod/__init__.py
dynamicmethod/__init__.pyc
dynamicmethod/__meta__.py
dynamicmethod/__pycache__/__init__.cpython-34.pyc
dynamicmethod/__pycache__/__init__.cpython-35.pyc
dynamicmethod/__pycache__/__init__.cpython-36.pyc
dynamicmethod/__pycache__/__init__.cpython-38.pyc
dynamicmethod/__pycache__/__meta__.cpython-34.pyc
dynamicmethod/__pycache__/__meta__.cpython-38.pyc
dynamicmethod-1.1.0.dist-info/LICENSE
dynamicmethod-1.1.0.dist-info/METADATA
dynamicmethod-1.1.0.dist-info/WHEEL
dynamicmethod-1.1.0.dist-info/top_level.txt
dynamicmethod-1.1.0.dist-info/RECORD
