Metadata-Version: 2.1
Name: dynamicmethod
Version: 1.1.0
Summary: An instance method decorator that also works as a classmethod.
Home-page: https://github.com/justengel/dynamicmethod
Author: Justin Engel
Author-email: jtengel08@gmail.com
License: MIT
Download-URL: https://github.com/justengel/dynamicmethod/archive/v1.1.0.tar.gz
Keywords: staticmethod classmethod instance dynamic class_instance_method
Platform: any
Classifier: Programming Language :: Python
Classifier: Programming Language :: Python :: 3
Classifier: Operating System :: OS Independent
